ml_api_client/__init__.py
ml_api_client/api_client.py
ml_api_client/models.py
ml_api_client/py.typed
ml_api_client/utils.py
ml_api_client/endpoints/__init__.py
ml_api_client/endpoints/auth.py
ml_api_client/endpoints/chat.py
ml_api_client/endpoints/embeddings.py
ml_api_client/endpoints/models.py
ml_api_client/endpoints/vector_stores.py
ml_api_client/modules/__init__.py
ml_api_client/modules/tools.py
ml_api_client-0.3.2.dist-info/licenses/LICENSE
ml_api_client-0.3.2.dist-info/METADATA
ml_api_client-0.3.2.dist-info/WHEEL
ml_api_client-0.3.2.dist-info/top_level.txt
ml_api_client-0.3.2.dist-info/RECORD
