Metadata-Version: 2.4
Name: ml_api_client
Version: 0.3.2
Summary: A Python client for interacting with Mathis LAMBERT's API
Author-email: Mathis LAMBERT <mathislambert.dev@gmail.com>
License: MIT License
Project-URL: Homepage, https://github.com/mathis-lambert/ml_api_client
Project-URL: Repository, https://github.com/mathis-lambert/ml_api_client
Project-URL: Issues, https://github.com/mathis-lambert/ml_api_client/issues
Keywords: api,client,llm,chat,embeddings,vector,openai-compatible
Classifier: Development Status :: 3 - Alpha
Classifier: Intended Audience :: Developers
Classifier: License :: OSI Approved :: MIT License
Classifier: Programming Language :: Python
Classifier: Programming Language :: Python :: 3
Classifier: Programming Language :: Python :: 3 :: Only
Classifier: Programming Language :: Python :: 3.10
Classifier: Programming Language :: Python :: 3.11
Classifier: Programming Language :: Python :: 3.12
Classifier: Programming Language :: Python :: 3.13
Classifier: Operating System :: OS Independent
Classifier: Typing :: Typed
Classifier: Topic :: Software Development :: Libraries :: Python Modules
Requires-Python: >=3.10
License-File: LICENSE
Requires-Dist: aiohttp>=3.11.12
Requires-Dist: pydantic>=2.10.6
Requires-Dist: openai
Provides-Extra: dev
Requires-Dist: fastapi[standard]>=0.115.8; extra == "dev"
Requires-Dist: pytest; extra == "dev"
Requires-Dist: pytest-asyncio; extra == "dev"
Requires-Dist: black; extra == "dev"
Requires-Dist: isort; extra == "dev"
Requires-Dist: ruff; extra == "dev"
Requires-Dist: flake8; extra == "dev"
Requires-Dist: python-dotenv; extra == "dev"
Requires-Dist: build; extra == "dev"
Requires-Dist: twine; extra == "dev"
Dynamic: license-file
